st_img_selectbox/__init__.py
st_img_selectbox/example.py
st_img_selectbox/frontend/build/asset-manifest.json
st_img_selectbox/frontend/build/bootstrap.min.css
st_img_selectbox/frontend/build/index.html
st_img_selectbox/frontend/build/static/js/main.a2bf13dc.js
st_img_selectbox/frontend/build/static/js/main.a2bf13dc.js.LICENSE.txt
st_img_selectbox/frontend/build/static/js/main.a2bf13dc.js.map
st_img_selectbox-0.0.1.dist-info/LICENSE
st_img_selectbox-0.0.1.dist-info/METADATA
st_img_selectbox-0.0.1.dist-info/WHEEL
st_img_selectbox-0.0.1.dist-info/top_level.txt
st_img_selectbox-0.0.1.dist-info/RECORD
